django_moncash/__init__.py
django_moncash/_utils.py
django_moncash/admin.py
django_moncash/apps.py
django_moncash/models.py
django_moncash/tests.py
django_moncash/urls.py
django_moncash/utils.py
django_moncash/views.py
django_moncash/migrations/0001_initial.py
django_moncash/migrations/0002_alter_transaction_user.py
django_moncash/migrations/0003_transaction_transaction_id.py
django_moncash/migrations/__init__.py
django_moncash-2.6.0.dist-info/LICENSE
django_moncash-2.6.0.dist-info/METADATA
django_moncash-2.6.0.dist-info/WHEEL
django_moncash-2.6.0.dist-info/top_level.txt
django_moncash-2.6.0.dist-info/RECORD
