Metadata-Version: 2.1
Name: django_moncash
Version: 2.6.0
Summary: Installable django moncash
Home-page: https://github.com/undisplay/django_moncash
Author-email: Freedy Meritus <meritusfreedy@gmail.com>
License:                     GNU GENERAL PUBLIC LICENSE
Project-URL: Homepage, https://github.com/undisplay/django_moncash
Keywords: moncash,django,payment,SDK
Classifier: License :: OSI Approved :: GNU General Public License v3 (GPLv3)
Classifier: Programming Language :: Python
Classifier: Programming Language :: Python :: 3
Requires-Python: >=3.6
License-File: LICENSE
Requires-Dist: Django>=2.2
Requires-Dist: moncash>=1.0.3
Provides-Extra: dev
Requires-Dist: pip-tools; extra == "dev"
Requires-Dist: pytest; extra == "dev"
